magiclens/__init__.py
magiclens/__main__.py
magiclens/cli.py
magiclens/content_detectors/__init__.py
magiclens/content_detectors/base.py
magiclens/content_detectors/discovery.py
magiclens/content_detectors/manager.py
magiclens/content_detectors/registry.py
magiclens/content_detectors/types/__init__.py
magiclens/content_detectors/types/baidu.py
magiclens/content_detectors/types/wechat.py
magiclens/content_detectors/types/zhihu.py
magiclens/content_processors/__init__.py
magiclens/content_processors/base.py
magiclens/content_processors/registry.py
magiclens/content_processors/types/__init__.py
magiclens/content_processors/types/baidu.py
magiclens/content_processors/types/wechat.py
magiclens/content_processors/types/zhihu.py
magiclens/converters/__init__.py
magiclens/converters/base.py
magiclens/converters/html2md.py
magiclens/converters/rules.py
magiclens/core/__init__.py
magiclens/core/registry.py
magiclens/core/rule.py
magiclens/core/service.py
magiclens/rules/__init__.py
magiclens/rules/html2md.py
magiclens/utils/__init__.py
magiclens-0.3.0.dist-info/METADATA
magiclens-0.3.0.dist-info/WHEEL
magiclens-0.3.0.dist-info/entry_points.txt
magiclens-0.3.0.dist-info/top_level.txt
magiclens-0.3.0.dist-info/RECORD
