Metadata-Version: 2.4
Name: magiclens
Version: 0.3.0
Summary: 强大的网页解析引擎，可以从HTML中提取结构化数据
Home-page: https://github.com/magiclens/magiclens
Author: MagicLens Team
Author-email: cc@dtyq.com
Maintainer: MagicLens Team
License: MIT
Project-URL: Homepage, https://github.com/yourusername/magiclens
Project-URL: Issues, https://github.com/yourusername/magiclens/issues
Project-URL: Documentation, https://magiclens.readthedocs.io/
Classifier: Development Status :: 3 - Alpha
Classifier: Intended Audience :: Developers
Classifier: License :: OSI Approved :: MIT License
Classifier: Programming Language :: Python :: 3
Classifier: Programming Language :: Python :: 3.7
Classifier: Programming Language :: Python :: 3.8
Classifier: Programming Language :: Python :: 3.9
Classifier: Programming Language :: Python :: 3.10
Classifier: Topic :: Internet :: WWW/HTTP
Classifier: Topic :: Text Processing :: Markup :: HTML
Requires-Python: >=3.8
Requires-Dist: beautifulsoup4>=4.9.0
Requires-Dist: lxml>=4.6.0
Requires-Dist: requests>=2.25.0
Provides-Extra: dev
Requires-Dist: pytest>=7.0.0; extra == "dev"
Requires-Dist: pytest-cov>=3.0.0; extra == "dev"
Requires-Dist: ruff>=0.0.240; extra == "dev"
Requires-Dist: mypy>=0.910; extra == "dev"
Requires-Dist: black>=22.1.0; extra == "dev"
Provides-Extra: docs
Requires-Dist: sphinx>=4.3.0; extra == "docs"
Requires-Dist: sphinx-rtd-theme>=1.0.0; extra == "docs"
Dynamic: author-email
Dynamic: home-page
Dynamic: requires-python
